README.rst
setup.py
pingdom/__init__.py
pingdom/connection.py
pingdom/exception.py
pingdom/resources.py
pingdom.egg-info/PKG-INFO
pingdom.egg-info/SOURCES.txt
pingdom.egg-info/dependency_links.txt
pingdom.egg-info/requires.txt
pingdom.egg-info/top_level.txt