Metadata-Version: 1.0
Name: pingdom
Version: 0.2.1
Summary: Pingdom Library
Home-page: https://github.com/mbabineau/pingdom-python
Author: Mike Babineau
Author-email: michael.babineau@gmail.com
License: Apache v2.0
Platform: Posix; MacOS X; Windows
Classifier: Development Status :: 3 - Alpha
Classifier: Intended Audience :: Developers
Classifier: Intended Audience :: System Administrators
Classifier: License :: OSI Approved :: Apache Software License
Classifier: Operating System :: OS Independent
Classifier: Topic :: System :: Monitoring
